{
  "modid": "CarpentersBlocks",
  "segments": [
    {
      "class": "com.carpentersblocks.block.BlockCarpentersButton",
      "type": "block",
      "actions": "RIGHT_CLICK",
      "meta": -1,
      "flags": "ACTIVATE",
      "priority": "HIGH"
    },
    {
      "class": "com.carpentersblocks.block.BlockCarpentersDoor",
      "type": "block",
      "actions": "RIGHT_CLICK",
      "meta": -1,
      "flags": "ACTIVATE",
      "priority": "HIGH"
    },
    {
      "class": "com.carpentersblocks.block.BlockCarpentersLever",
      "type": "block",
      "actions": "RIGHT_CLICK",
      "meta": -1,
      "flags": "ACTIVATE",
      "priority": "HIGH"
    },
    {
      "class": "com.carpentersblocks.block.BlockCarpentersGate",
      "type": "block",
      "actions": "RIGHT_CLICK",
      "meta": -1,
      "flags": "ACTIVATE",
      "priority": "HIGH"
    },
    {
      "class": "com.carpentersblocks.block.BlockCarpentersHatch",
      "type": "block",
      "actions": "RIGHT_CLICK",
      "meta": -1,
      "flags": "ACTIVATE",
      "priority": "HIGH"
    }
  ]
}
